hk_horn/__init__.py
hk_horn/api.py
hk_horn/cli/__init__.py
hk_horn/cli/__main__.py
hk_horn/consts.py
hk_horn/enums.py
horn.py
hk_horn/models.py
hk_horn/type_annotations.py
hk_horn-0.0.9.dist-info/LICENSE
hk_horn-0.0.9.dist-info/METADATA
hk_horn-0.0.9.dist-info/WHEEL
hk_horn-0.0.9.dist-info/entry_points.txt
hk_horn-0.0.9.dist-info/RECORD
