Metadata-Version: 2.1
Name: hk-horn
Version: 0.0.9
Summary: Hollow Knight Mods Manager =)
License: Apache 2.0
Keywords: package-manager,mod,mod-manager,hollow-knight
Author: BlackCatDevel0per
Author-email: bcdev@mail.ru
Requires-Python: >=3.8,<4.0
Classifier: Development Status :: 5 - Production/Stable
Classifier: Environment :: Console
Classifier: Framework :: AsyncIO
Classifier: Intended Audience :: Developers
Classifier: Intended Audience :: System Administrators
Classifier: License :: OSI Approved :: Apache Software License
Classifier: License :: Other/Proprietary License
Classifier: Programming Language :: Python :: 3
Classifier: Programming Language :: Python :: 3.8
Classifier: Programming Language :: Python :: 3.9
Classifier: Programming Language :: Python :: 3.10
Classifier: Programming Language :: Python :: 3.11
Classifier: Programming Language :: Python :: 3.12
Classifier: Programming Language :: Python :: Implementation :: PyPy
Classifier: Topic :: Communications :: Chat
Classifier: Topic :: Software Development :: Libraries :: Python Modules
Classifier: Typing :: Typed
Requires-Dist: click (>=8.1.7,<9.0.0)
Requires-Dist: filetype (>=1.2.0,<2.0.0)
Requires-Dist: lxml (>=4.9.3,<5.0.0)
Requires-Dist: platformdirs (>=4.0.0,<5.0.0)
Requires-Dist: pytermgui (>=7.7.0,<8.0.0)
Requires-Dist: requests (>=2.31.0,<3.0.0)
Requires-Dist: rich (>=13.6.0,<14.0.0)
Project-URL: Documentation, https://github.com/BlackCatDevel0per/hk-horn
Project-URL: Homepage, https://github.com/BlackCatDevel0per/hk-horn
Project-URL: Repository, https://github.com/BlackCatDevel0per/hk-horn
